subtitlfy/__init__.py
subtitlfy/__main__.py
subtitlfy/cli.py
subtitlfy/editor.py
subtitlfy-0.1.0.dist-info/METADATA
subtitlfy-0.1.0.dist-info/WHEEL
subtitlfy-0.1.0.dist-info/entry_points.txt
subtitlfy-0.1.0.dist-info/top_level.txt
subtitlfy-0.1.0.dist-info/RECORD
